<?xml version="1.0" encoding="UTF-8"?>
<speciesPage><NAME_CD>COOR</NAME_CD><group>PLANT</group><desc><growthForm>DUMMYDATA</growthForm><size>Annual herb, to 0.8 m tall, erect.</size><parts><part><partName>Lower leaves</partName><partText>narrowed to the base.</partText></part><part><partName>Upper leaves</partName><partText>alternate, clasping, pale, oval to elliptic or oblong, bases heart-shaped, tips broadly rounded, margins non-toothed.</partText></part><part><partName>Flowers</partName><partText>in a dense, branched cluster (raceme), which is borne terminally on a stem. Sepals erect. Petals four, cream-colored to yellowish white, 1 - 1.2 cm long. Stamens six.</partText></part><part><partName>Fruit</partName><partText>a long, narrow pod (silique), widely spreading, often slightly drooping, 8 - 12 cm long, 2 - 3 mm wide, four-angled.</partText></part><part><partName/><partText/></part><part><partName/><partText/></part><part><partName/><partText/></part><part><partName/><partText/></part><part><partName/><partText/></part><part><partName/><partText/></part></parts></desc><similarSpecies><comments/><nameCds><simNmCd/><simNmCd/><simNmCd/><simNmCd/><simNmCd/><simNmCd/></nameCds><links><link><linkUri/><linkText/></link><link><linkUri/><linkText/></link></links></similarSpecies><flowering>mid May to early June</flowering><habitatEcology>&lt;i&gt;Conringia orientalis&lt;/i&gt; was once more common in the Chicago Region. It has been found growing near a ditch, in a cultivated field overgrown with weeds, and along a railroad. Look for it along railroads and in disturbed areas.</habitatEcology><nativity>non-native</nativity><notes><comments>Introduced from Europe.</comments><links><link><linkUri/><linkText/></link><link><linkUri/><linkText/></link><link><linkUri/><linkText/></link></links></notes><etymology><comments>&lt;i&gt;Conringia&lt;/i&gt; is named after H. Conring (1606-1681), a professor at Helmstadt, Germany. &lt;i&gt;Orientalis&lt;/i&gt; means “oriental.”</comments><links><link><linkUri/><linkText/></link><link><linkUri/><linkText/></link><link><linkUri/><linkText/></link></links></etymology><furtherInfo><comments/><links><link><linkUri/><linkText/></link><link><linkUri/><linkText/></link><link><linkUri/><linkText/></link><link><linkUri/><linkText/></link><link><linkUri/><linkText/></link><link><linkUri/><linkText/></link><link><linkUri/><linkText/></link><link><linkUri/><linkText/></link><link><linkUri/><linkText/></link><link><linkUri/><linkText/></link></links></furtherInfo><references><reference><citation/></reference><reference><citation/></reference><reference><citation/></reference><reference><citation/></reference><reference><citation/></reference><reference><citation/></reference><reference><citation/></reference><reference><citation/></reference><reference><citation/></reference><reference><citation/></reference><reference><link><linkUri/><linkText/></link></reference><reference><link><linkUri/><linkText/></link></reference><reference><link><linkUri/><linkText/></link></reference><reference><link><linkUri/><linkText/></link></reference><reference><link><linkUri/><linkText/></link></reference><reference><link><linkUri/><linkText/></link></reference><reference><link><linkUri/><linkText/></link></reference><reference><link><linkUri/><linkText/></link></reference><reference><link><linkUri/><linkText/></link></reference><reference><link><linkUri/><linkText/></link></reference></references><otherRecords><ilBn>has other records</ilBn><ilCk>has other records</ilCk><ilDk>has other records</ilDk><ilDp>has other records</ilDp><ilGd/><ilKd/><ilKk/><ilKn/><ilLk>has other records</ilLk><ilMh/><ilWl/><inJs>has other records</inJs><inLk>has other records</inLk><inLp>has other records</inLp><inNt>has other records</inNt><inPt/><inSj/><inSk/><miBr/><wiKs/><wiMw/><wiRc>has other records</wiRc><wiWk/><wiWw/></otherRecords></speciesPage>